[
  { "type": "constructor", "inputs": [], "stateMutability": "nonpayable" },
  {
    "type": "function",
    "name": "UPGRADE_INTERFACE_VERSION",
    "inputs": [],
    "outputs": [{ "name": "", "type": "string", "internalType": "string" }],
    "stateMutability": "view"
  },
  {
    "type": "function",
    "name": "accessControl",
    "inputs": [],
    "outputs": [
      {
        "name": "",
        "type": "address",
        "internalType": "contract ISystemAccessControl"
      }
    ],
    "stateMutability": "view"
  },
  {
    "type": "function",
    "name": "getAllModuleKeys",
    "inputs": [],
    "outputs": [
      { "name": "keys", "type": "bytes32[]", "internalType": "bytes32[]" }
    ],
    "stateMutability": "view"
  },
  {
    "type": "function",
    "name": "getModuleFactory",
    "inputs": [{ "name": "key", "type": "bytes32", "internalType": "bytes32" }],
    "outputs": [{ "name": "", "type": "address", "internalType": "address" }],
    "stateMutability": "view"
  },
  {
    "type": "function",
    "name": "getOrgModules",
    "inputs": [{ "name": "orgId", "type": "uint48", "internalType": "uint48" }],
    "outputs": [
      { "name": "keys", "type": "bytes32[]", "internalType": "bytes32[]" }
    ],
    "stateMutability": "view"
  },
  {
    "type": "function",
    "name": "initialize",
    "inputs": [
      {
        "name": "accessControlAddress",
        "type": "address",
        "internalType": "address"
      }
    ],
    "outputs": [],
    "stateMutability": "nonpayable"
  },
  {
    "type": "function",
    "name": "isModuleActive",
    "inputs": [{ "name": "key", "type": "bytes32", "internalType": "bytes32" }],
    "outputs": [{ "name": "", "type": "bool", "internalType": "bool" }],
    "stateMutability": "view"
  },
  {
    "type": "function",
    "name": "isOrgSubscribed",
    "inputs": [
      { "name": "orgId", "type": "uint48", "internalType": "uint48" },
      { "name": "moduleKey", "type": "bytes32", "internalType": "bytes32" }
    ],
    "outputs": [{ "name": "", "type": "bool", "internalType": "bool" }],
    "stateMutability": "view"
  },
  {
    "type": "function",
    "name": "moduleDefinitions",
    "inputs": [{ "name": "", "type": "bytes32", "internalType": "bytes32" }],
    "outputs": [
      { "name": "key", "type": "bytes32", "internalType": "bytes32" },
      { "name": "name", "type": "string", "internalType": "string" },
      { "name": "factory", "type": "address", "internalType": "address" },
      { "name": "active", "type": "bool", "internalType": "bool" },
      { "name": "exists", "type": "bool", "internalType": "bool" }
    ],
    "stateMutability": "view"
  },
  {
    "type": "function",
    "name": "proxiableUUID",
    "inputs": [],
    "outputs": [{ "name": "", "type": "bytes32", "internalType": "bytes32" }],
    "stateMutability": "view"
  },
  {
    "type": "function",
    "name": "registerModule",
    "inputs": [
      { "name": "key", "type": "bytes32", "internalType": "bytes32" },
      { "name": "name", "type": "string", "internalType": "string" },
      { "name": "factory", "type": "address", "internalType": "address" }
    ],
    "outputs": [],
    "stateMutability": "nonpayable"
  },
  {
    "type": "function",
    "name": "setModuleActive",
    "inputs": [
      { "name": "key", "type": "bytes32", "internalType": "bytes32" },
      { "name": "active", "type": "bool", "internalType": "bool" }
    ],
    "outputs": [],
    "stateMutability": "nonpayable"
  },
  {
    "type": "function",
    "name": "subscribeOrgToModule",
    "inputs": [
      { "name": "orgId", "type": "uint48", "internalType": "uint48" },
      { "name": "moduleKey", "type": "bytes32", "internalType": "bytes32" }
    ],
    "outputs": [],
    "stateMutability": "nonpayable"
  },
  {
    "type": "function",
    "name": "unsubscribeOrgFromModule",
    "inputs": [
      { "name": "orgId", "type": "uint48", "internalType": "uint48" },
      { "name": "moduleKey", "type": "bytes32", "internalType": "bytes32" }
    ],
    "outputs": [],
    "stateMutability": "nonpayable"
  },
  {
    "type": "function",
    "name": "updateModuleFactory",
    "inputs": [
      { "name": "key", "type": "bytes32", "internalType": "bytes32" },
      { "name": "newFactory", "type": "address", "internalType": "address" }
    ],
    "outputs": [],
    "stateMutability": "nonpayable"
  },
  {
    "type": "function",
    "name": "upgradeToAndCall",
    "inputs": [
      {
        "name": "newImplementation",
        "type": "address",
        "internalType": "address"
      },
      { "name": "data", "type": "bytes", "internalType": "bytes" }
    ],
    "outputs": [],
    "stateMutability": "payable"
  },
  {
    "type": "event",
    "name": "Initialized",
    "inputs": [
      {
        "name": "version",
        "type": "uint64",
        "indexed": false,
        "internalType": "uint64"
      }
    ],
    "anonymous": false
  },
  {
    "type": "event",
    "name": "ModuleRegistered",
    "inputs": [
      {
        "name": "key",
        "type": "bytes32",
        "indexed": true,
        "internalType": "bytes32"
      },
      {
        "name": "name",
        "type": "string",
        "indexed": false,
        "internalType": "string"
      },
      {
        "name": "factory",
        "type": "address",
        "indexed": false,
        "internalType": "address"
      }
    ],
    "anonymous": false
  },
  {
    "type": "event",
    "name": "ModuleStatusChanged",
    "inputs": [
      {
        "name": "key",
        "type": "bytes32",
        "indexed": true,
        "internalType": "bytes32"
      },
      {
        "name": "active",
        "type": "bool",
        "indexed": false,
        "internalType": "bool"
      }
    ],
    "anonymous": false
  },
  {
    "type": "event",
    "name": "ModuleUpdated",
    "inputs": [
      {
        "name": "key",
        "type": "bytes32",
        "indexed": true,
        "internalType": "bytes32"
      },
      {
        "name": "newFactory",
        "type": "address",
        "indexed": false,
        "internalType": "address"
      }
    ],
    "anonymous": false
  },
  {
    "type": "event",
    "name": "OrgModuleSubscribed",
    "inputs": [
      {
        "name": "orgId",
        "type": "uint48",
        "indexed": true,
        "internalType": "uint48"
      },
      {
        "name": "moduleKey",
        "type": "bytes32",
        "indexed": true,
        "internalType": "bytes32"
      }
    ],
    "anonymous": false
  },
  {
    "type": "event",
    "name": "OrgModuleUnsubscribed",
    "inputs": [
      {
        "name": "orgId",
        "type": "uint48",
        "indexed": true,
        "internalType": "uint48"
      },
      {
        "name": "moduleKey",
        "type": "bytes32",
        "indexed": true,
        "internalType": "bytes32"
      }
    ],
    "anonymous": false
  },
  {
    "type": "event",
    "name": "Upgraded",
    "inputs": [
      {
        "name": "implementation",
        "type": "address",
        "indexed": true,
        "internalType": "address"
      }
    ],
    "anonymous": false
  },
  {
    "type": "error",
    "name": "AddressEmptyCode",
    "inputs": [
      { "name": "target", "type": "address", "internalType": "address" }
    ]
  },
  {
    "type": "error",
    "name": "ERC1967InvalidImplementation",
    "inputs": [
      {
        "name": "implementation",
        "type": "address",
        "internalType": "address"
      }
    ]
  },
  { "type": "error", "name": "ERC1967NonPayable", "inputs": [] },
  { "type": "error", "name": "FailedCall", "inputs": [] },
  { "type": "error", "name": "InvalidAddress", "inputs": [] },
  { "type": "error", "name": "InvalidInitialization", "inputs": [] },
  { "type": "error", "name": "ModuleAlreadyRegistered", "inputs": [] },
  { "type": "error", "name": "ModuleNotActive", "inputs": [] },
  { "type": "error", "name": "ModuleNotFound", "inputs": [] },
  { "type": "error", "name": "NotInitializing", "inputs": [] },
  { "type": "error", "name": "OrgAlreadySubscribed", "inputs": [] },
  { "type": "error", "name": "OrgNotSubscribed", "inputs": [] },
  { "type": "error", "name": "UUPSUnauthorizedCallContext", "inputs": [] },
  {
    "type": "error",
    "name": "UUPSUnsupportedProxiableUUID",
    "inputs": [{ "name": "slot", "type": "bytes32", "internalType": "bytes32" }]
  },
  { "type": "error", "name": "Unauthorized", "inputs": [] }
]
